svolfit/__init__.py
svolfit/analysis_timeseries.py
svolfit/estimationstats.py
svolfit/gridanalysis.py
svolfit/gridanalysis_correlation.py
svolfit/svolfit.py
svolfit/data/__init__.py
svolfit/estimatestats/__init__.py
svolfit/estimatestats/gnuplot_utils.py
svolfit/estimatestats/latex_utils.py
svolfit/estimatestats/pathsim.py
svolfit/estimatestats/simparamstats.py
svolfit/models/B32.py
svolfit/models/B32_utils.py
svolfit/models/Bates.py
svolfit/models/Bates_utils.py
svolfit/models/GARCHdiff.py
svolfit/models/GARCHdiff_utils.py
svolfit/models/GARCHjdiff.py
svolfit/models/GARCHjdiff_utils.py
svolfit/models/GBM.py
svolfit/models/GBM_utils.py
svolfit/models/H32.py
svolfit/models/H32_utils.py
svolfit/models/Heston.py
svolfit/models/HestonNandi.py
svolfit/models/HestonNandi_utils.py
svolfit/models/Heston_GBM.py
svolfit/models/Heston_GBM_utils.py
svolfit/models/Heston_utils.py
svolfit/models/LognormalJump.py
svolfit/models/LognormalJump_utils.py
svolfit/models/MertonJD.py
svolfit/models/MertonJD_utils.py
svolfit/models/PureJump.py
svolfit/models/PureJump_utils.py
svolfit/models/Template.py
svolfit/models/__init__.py
svolfit/models/model_factory.py
svolfit/models/model_utils.py
svolfit/models/svol_model.py
svolfit/models/template.py
svolfit/timeseries_utils/__init__.py
svolfit/timeseries_utils/gnuplot_utils.py
svolfit/timeseries_utils/latex_utils.py
svolfit/timeseries_utils/tsparamstats.py
tests/__init__.py
tests/test_calc.py
tests/test_fits.py
tests/__pycache__/__init__.cpython-37.pyc
tests/__pycache__/__init__.cpython-38.pyc
tests/__pycache__/test_calc.cpython-38-pytest-6.2.2.pyc
tests/__pycache__/test_fits.cpython-37-pytest-6.2.1.pyc
tests/__pycache__/test_fits.cpython-38-pytest-6.2.1.pyc
tests/__pycache__/test_fits.cpython-38-pytest-6.2.2.pyc
tests/data/test_path.csv
svolfit-0.0.8.dist-info/LICENSE.txt
svolfit-0.0.8.dist-info/METADATA
svolfit-0.0.8.dist-info/WHEEL
svolfit-0.0.8.dist-info/top_level.txt
svolfit-0.0.8.dist-info/RECORD
